samplepath/__init__.py
samplepath/__main__.py
samplepath/cli.py
samplepath/csv_loader.py
samplepath/file_utils.py
samplepath/filter.py
samplepath/limits.py
samplepath/metrics.py
samplepath/point_process.py
samplepath/sample_path_analysis.py
samplepath/plots/__init__.py
samplepath/plots/advanced.py
samplepath/plots/convergence.py
samplepath/plots/core.py
samplepath/plots/helpers.py
samplepath/plots/misc.py
samplepath/plots/stability.py
samplepath-0.1.4.dist-info/METADATA
samplepath-0.1.4.dist-info/WHEEL
samplepath-0.1.4.dist-info/entry_points.txt
samplepath-0.1.4.dist-info/licenses/LICENSE
samplepath-0.1.4.dist-info/RECORD
