Metadata-Version: 2.4
Name: samplepath
Version: 0.1.4
Summary: Sample Path Analysis Library
Project-URL: Homepage, https://samplepath.pcalc.org
Project-URL: Repository, https://github.com/presence-calculus/samplepath-flow.git
Author-email: Krishna Kumar <kkumar@exathink.com>
License: MIT
License-File: LICENSE
Keywords: analytics,flow,presence,queueing
Classifier: License :: OSI Approved :: MIT License
Classifier: Operating System :: OS Independent
Classifier: Programming Language :: Python :: 3
Classifier: Programming Language :: Python :: 3.11
Classifier: Topic :: Scientific/Engineering
Classifier: Topic :: Software Development :: Libraries
Requires-Python: >=3.11
Requires-Dist: matplotlib<4.0,>=3.8
Requires-Dist: numpy<3.0,>=1.26
Requires-Dist: pandas<3.0,>=2.2
Requires-Dist: sortedcontainers<3.0.0,>=2.4.0
Provides-Extra: polars
Requires-Dist: polars; extra == 'polars'
